src/rs-result/__init__.py
rs_result-0.0.1.dist-info/METADATA
rs_result-0.0.1.dist-info/WHEEL
rs_result-0.0.1.dist-info/licenses/LICENSE
rs_result-0.0.1.dist-info/RECORD
